CHANGELOG.md
MANIFEST.in
Pipfile
README.md
setup.cfg
setup.py
easy_geoparsing/__init__.py
easy_geoparsing/parser.py
easy_geoparsing.egg-info/PKG-INFO
easy_geoparsing.egg-info/SOURCES.txt
easy_geoparsing.egg-info/dependency_links.txt
easy_geoparsing.egg-info/requires.txt
easy_geoparsing.egg-info/top_level.txt