Metadata-Version: 2.1
Name: easy-geoparsing
Version: 1.2.0
Summary: Easy-to-use module for streamlined parsing of countries from locations
Home-page: UNKNOWN
Author: PaddyAlton
Author-email: paddy.alton@apolitical.co
License: UNKNOWN
Download-URL: https://github.com/apolitical/easy-geoparsing/archive/v1.2.0.tar.gz
Platform: UNKNOWN
